coacd/lib_coacd.dylib
coacd/__init__.py
coacd-1.0.7.data/scripts/coacd
coacd-1.0.7.dist-info/RECORD
coacd-1.0.7.dist-info/WHEEL
coacd-1.0.7.dist-info/top_level.txt
coacd-1.0.7.dist-info/METADATA
coacd-1.0.7.dist-info/licenses/LICENSE
